LICENSE
throttled/__init__.py
throttled/exceptions.py
throttled/fastapi/__init__.py
throttled/fastapi/base.py
throttled/fastapi/limiters.py
throttled/fastapi/utils.py
throttled/limiter.py
throttled/models.py
throttled/py.typed
throttled/storage/__init__.py
throttled/storage/_abstract.py
throttled/storage/_duration.py
throttled/storage/memory.py
throttled/storage/redis.py
throttled/strategies.py
throttled-0.2.1.dist-info/LICENSE
throttled-0.2.1.dist-info/WHEEL
throttled-0.2.1.dist-info/METADATA
throttled-0.2.1.dist-info/RECORD
